ggci/__init__.py
ggci/commons.py
ggci/config.py
ggci/forwarder.py
ggci/gitlab.py
ggci/google_chat.py
ggci-1.2.17.dist-info/LICENSE
ggci-1.2.17.dist-info/WHEEL
ggci-1.2.17.dist-info/METADATA
ggci-1.2.17.dist-info/RECORD
