Metadata-Version: 2.1
Name: ggci
Version: 1.2.17
Summary: GitLab Google Chat Integration
Home-page: https://gitlab.com/jan.lukany/ggci
License: MIT
Author: Jan Lukány
Author-email: lukany.jan@gmail.com
Requires-Python: >=3.7,<4.0
Classifier: Framework :: Flask
Classifier: Intended Audience :: Developers
Classifier: License :: OSI Approved :: MIT License
Classifier: Programming Language :: Python :: 3
Classifier: Programming Language :: Python :: 3.10
Classifier: Programming Language :: Python :: 3.7
Classifier: Programming Language :: Python :: 3.8
Classifier: Programming Language :: Python :: 3.9
Classifier: Topic :: Communications :: Chat
Classifier: Topic :: Internet :: WWW/HTTP :: WSGI
Classifier: Topic :: Internet :: WWW/HTTP :: WSGI :: Application
Classifier: Topic :: Software Development :: Version Control
Classifier: Topic :: Software Development :: Version Control :: Git
Requires-Dist: flask (>=1.1.2,<3.0)
Requires-Dist: flexmock (>=0.10.4,<0.11.0)
Requires-Dist: pyyaml (>=5.4.1,<6.0.0)
Requires-Dist: requests (>=2.25.1,<3.0.0)
Requires-Dist: tenacity (>=7.0.0,<8.0.0)
Project-URL: Repository, https://gitlab.com/jan.lukany/ggci
